{"version": "1.0.0", "state": {"run_id": "2135c5ef", "seed": 534682671, "turn": 0, "depth": 1, "branch": "main", "kills": 0, "gold_found": 0, "items_identified": 0, "start_time": 1782117105.0140598, "death_cause": null, "player_name": "Adventurer", "player_class": "warrior", "flags": []}, "player": {"x": 10, "y": 10, "hp": 15, "max_hp": 23, "power": 5, "defense": 2, "speed": 100, "level": 1, "xp": 0, "xp_to_next": 100, "skill_points": 0, "known_skills": [], "nutrition": 2000, "gold": 0, "kill_count": 0, "stats": {"cha": 8, "con": 13, "dex": 10, "int": 8, "str": 14, "wis": 10}, "effects": {}, "identified_types": [], "inventory": {"max_weight": 100, "items": [], "equipment": {"head": null, "chest": null, "hands": null, "legs": null, "feet": null, "main_hand": null, "off_hand": null}}}, "dungeon_map": [[false, false, false, false, false, false, false, false, false, false, false, false, false, false, false, false, false, false, false, false, false, false, false, false, false, false, false, false, false, false, false, false, false, false, false, false, false, false, false, false, false, false, false], [false, false, false, false, false, false, false, false, false, false, false, false, false, false, false, false, false, false, false, false, false, false, false, false, false, false, false, false, false, false, false, false, true, true, true, true, true, true, true, false, false, false, false], [false, false, false, false, false, false, false, false, false, false, false, false, false, false, false, false, false, false, false, false, false, false, false, false, false, false, false, false, false, false, false, false, true, true, true, true, true, true, true, false, false, false, false], [false, false, false, false, false, false, false, false, false, false, false, false, false, false, false, false, false, false, false, false, false, false, false, false, false, false, false, false, false, false, false, false, true, true, true, true, true, true, true, false, false, false, false], [false, false, false, false, false, false, false, false, false, false, false, false, false, false, false, false, false, false, false, false, false, false, false, false, false, false, false, false, false, false, false, false, true, true, true, true, true, true, true, false, false, false, false], [false, false, false, false, false, false, false, false, false, false, false, false, false, false, false, false, true, true, true, true, true, true, true, true, true, true, true, true, false, false, false, false, true, true, true, true, true, true, true, false, false, false, false], [false, false, false, false, false, false, false, false, false, false, false, false, false, false, false, false, true, true, true, true, true, true, true, true, true, true, true, true, false, false, false, false, true, true, true, true, true, true, true, false, false, false, false], [false, false, false, false, false, false, false, false, false, false, false, false, false, false, false, false, true, true, true, true, true, true, true, true, true, true, true, true, false, false, false, false, true, true, true, true, true, true, true, false, false, false, false], [false, false, false, false, false, false, false, false, false, false, false, false, false, false, false, false, true, true, true, true, true, true, true, true, true, true, true, true, false, false, false, false, true, true, true, true, true, true, true, false, false, false, false], [false, false, false, false, false, false, false, false, false, false, false, false, false, false, false, false, true, true, true, true, true, true, true, true, true, true, true, true, false, false, false, false, true, true, true, true, true, true, true, false, false, false, false], [false, false, false, false, false, false, false, false, false, false, false, false, false, false, false, false, true, true, true, true, true, true, true, true, true, true, true, true, false, false, false, false, true, true, true, true, true, true, true, false, false, false, false], [false, false, false, false, false, false, false, false, false, false, false, false, false, false, false, false, false, false, false, false, false, true, false, false, false, false, false, false, false, false, false, false, true, true, true, true, true, true, true, false, false, false, false], [false, false, false, false, false, false, false, false, false, false, false, false, false, false, false, false, false, false, false, false, false, true, false, false, false, false, false, false, false, false, false, false, false, false, false, true, false, false, false, false, false, false, false], [false, false, false, false, false, false, false, false, false, false, false, false, false, false, false, false, false, false, false, false, false, true, false, false, false, false, false, false, false, false, false, false, false, false, false, true, false, false, false, false, false, false, false], [false, false, false, false, false, false, false, false, false, false, false, false, false, false, false, false, false, false, false, false, false, true, false, false, false, false, false, false, false, false, false, false, false, false, false, true, false, false, false, false, false, false, false], [false, false, false, false, false, false, false, false, false, false, false, false, false, false, false, false, false, false, false, false, false, true, false, false, false, true, true, true, true, true, true, true, true, true, true, true, true, true, false, false, false, false, false], [false, false, false, false, false, false, false, false, false, false, false, false, false, false, false, false, false, false, false, false, false, true, false, false, false, true, true, true, true, true, true, true, true, true, true, true, true, true, false, false, false, false, false], [false, false, false, false, false, false, false, false, false, false, false, false, false, false, false, false, false, false, false, false, false, true, false, false, false, true, true, true, true, true, true, true, true, true, true, true, true, true, false, false, false, false, false], [false, false, false, false, false, false, false, false, false, false, false, false, false, false, false, false, false, false, false, false, false, true, false, false, false, true, true, true, true, true, true, true, true, true, true, true, true, true, false, false, false, false, false], [false, false, true, true, true, true, true, true, true, true, true, true, true, true, false, false, false, false, false, false, false, true, false, false, false, true, true, true, true, true, true, true, true, true, true, true, true, true, false, false, false, false, false], [false, false, true, true, true, true, true, true, true, true, true, true, true, true, false, false, false, false, false, false, false, true, true, true, true, true, true, true, true, true, true, true, true, true, true, true, true, true, false, false, false, false, false], [false, false, true, true, true, true, true, true, true, true, true, true, true, true, false, false, false, false, false, false, false, true, false, false, false, true, true, true, true, true, true, true, true, true, true, true, true, true, false, false, false, false, false], [false, false, true, true, true, true, true, true, true, true, true, true, true, true, false, false, false, false, false, false, false, true, false, false, false, true, true, true, true, true, true, true, true, true, true, true, true, true, false, false, false, false, false], [false, false, true, true, true, true, true, true, true, true, true, true, true, true, false, false, false, false, false, false, false, true, false, false, false, true, true, true, true, true, true, true, true, true, true, true, true, true, false, false, false, false, false], [false, false, true, true, true, true, true, true, true, true, true, true, true, true, false, false, false, false, false, false, false, true, false, false, false, true, true, true, true, true, true, true, true, true, true, true, true, true, false, false, false, false, false], [false, false, true, true, true, true, true, true, true, true, true, true, true, true, false, false, false, false, false, false, false, true, false, false, false, true, true, true, true, true, true, true, true, true, true, true, true, true, false, false, false, false, false], [false, false, true, true, true, true, true, true, true, true, true, true, true, true, false, false, false, false, false, false, false, true, false, false, false, false, false, false, false, false, false, true, false, false, false, true, false, false, false, false, false, false, false], [false, false, true, true, true, true, true, true, true, true, true, true, true, true, false, false, false, false, false, false, false, true, false, false, false, false, false, false, false, false, false, true, false, false, false, true, false, false, false, false, false, false, false], [false, false, true, true, true, true, true, true, true, true, true, true, true, true, false, false, false, false, false, false, false, true, false, false, false, false, false, false, false, false, false, true, false, false, false, true, false, false, false, false, false, false, false], [false, false, false, false, false, false, false, true, false, false, false, false, false, false, false, false, false, false, false, false, false, true, false, false, false, false, false, false, false, false, false, true, false, false, false, true, false, false, false, false, false, false, false], [false, false, false, false, false, false, false, true, false, false, false, false, false, false, false, false, false, false, false, false, false, true, false, false, false, false, false, false, false, false, false, true, false, false, false, true, false, false, false, false, false, false, false], [false, false, false, false, false, false, false, true, false, false, false, false, false, false, false, false, false, false, false, false, false, true, false, false, false, false, false, false, false, false, false, true, false, false, false, true, false, false, false, false, false, false, false], [false, false, false, false, false, false, false, true, false, false, false, false, false, false, false, false, false, false, false, false, false, true, false, false, false, false, false, false, false, false, false, true, false, false, false, true, false, false, false, false, false, false, false], [false, false, false, false, false, false, false, true, false, false, false, false, false, false, false, false, false, false, false, false, false, true, false, false, false, false, false, false, false, false, false, true, false, false, false, true, false, false, false, false, false, false, false], [false, false, false, false, false, false, false, true, false, false, false, false, false, false, false, false, false, false, false, false, false, true, false, false, false, false, false, false, false, false, false, true, false, false, false, true, false, false, false, false, false, false, false], [false, false, false, false, false, false, false, true, false, false, false, false, false, false, false, false, false, false, false, false, false, true, false, false, false, false, false, false, false, false, false, true, false, false, false, true, false, false, false, false, false, false, false], [false, false, false, false, false, false, false, true, false, false, false, false, false, false, false, false, false, false, false, false, false, true, false, false, false, false, false, false, false, false, false, true, false, false, false, true, false, false, false, false, false, false, false], [false, false, false, false, false, false, false, true, false, false, false, false, false, false, false, false, false, false, false, false, false, true, false, false, false, false, false, false, false, false, false, true, false, false, false, true, false, false, false, false, false, false, false], [false, false, false, false, false, false, false, true, false, false, false, false, false, false, false, false, false, false, false, false, false, true, false, false, false, false, false, false, false, false, false, true, false, false, false, true, false, false, false, false, false, false, false], [false, false, false, false, false, false, false, true, false, false, false, false, false, false, false, false, false, false, false, false, false, true, false, false, false, false, false, false, false, false, false, true, false, false, false, true, false, false, false, false, false, false, false], [false, false, false, false, false, false, false, true, false, false, false, false, false, false, false, false, false, false, false, false, false, true, false, false, false, false, false, false, false, false, false, true, false, false, false, true, false, false, false, false, false, false, false], [false, false, false, false, false, false, false, true, false, false, false, false, false, false, false, false, false, false, false, false, false, true, false, false, false, false, false, false, false, false, false, true, false, false, false, true, false, false, false, false, false, false, false], [false, false, false, false, false, false, false, true, false, false, false, false, false, false, false, false, false, false, false, false, false, true, false, false, false, false, false, false, false, false, false, true, false, false, false, true, false, false, false, false, false, false, false], [false, false, false, false, false, false, false, true, false, false, false, false, false, false, false, false, false, false, false, false, false, true, false, false, false, false, false, false, false, false, false, true, false, false, false, true, false, false, false, false, false, false, false], [false, false, false, false, false, false, false, true, false, false, false, false, false, false, false, false, false, false, false, false, false, true, false, false, false, false, false, false, false, false, false, true, false, false, false, true, false, false, false, false, false, false, false], [false, false, false, false, false, false, false, true, false, false, false, false, false, false, false, false, false, false, false, false, false, true, false, false, false, false, false, false, false, false, false, true, false, false, false, true, false, false, false, false, false, false, false], [false, false, false, false, false, false, false, true, false, false, false, false, false, false, false, false, false, false, false, false, false, true, false, false, false, false, false, false, false, false, false, true, false, false, false, true, false, false, false, false, false, false, false], [false, false, false, false, false, false, false, true, false, false, false, false, false, false, false, false, false, false, false, false, false, true, false, false, false, false, false, false, false, false, false, true, false, false, false, true, false, false, false, false, false, false, false], [false, false, false, false, false, false, false, true, false, false, false, false, false, false, false, false, false, false, false, false, false, true, false, false, false, false, false, false, false, false, false, true, false, false, false, true, false, false, false, false, false, false, false], [false, false, false, false, false, false, false, true, false, false, false, false, false, false, false, false, false, false, false, false, false, true, false, false, false, false, false, false, false, false, false, true, false, false, false, true, false, false, false, false, false, false, false], [false, false, false, false, false, false, false, true, false, false, false, false, false, false, false, false, false, false, false, false, false, true, false, false, false, false, false, false, false, false, false, true, false, false, false, true, false, false, false, false, false, false, false], [false, false, false, false, false, false, false, true, false, false, false, false, false, false, false, false, false, false, false, false, false, true, false, false, false, false, false, false, false, false, false, true, false, false, false, true, false, false, false, false, false, false, false], [false, false, false, false, false, false, false, true, false, false, false, false, false, false, false, false, false, false, false, false, false, true, false, false, false, false, false, false, false, false, false, true, false, false, false, true, false, false, false, false, false, false, false], [false, false, false, false, false, false, false, true, false, false, false, false, false, false, false, false, false, false, false, false, false, true, false, false, false, false, false, false, false, false, false, true, false, false, false, true, false, false, false, false, false, false, false], [false, false, false, false, false, false, false, true, false, false, false, false, false, false, false, false, false, false, false, false, false, true, false, false, false, false, false, false, false, false, false, true, false, false, false, true, false, false, false, false, false, false, false], [false, false, false, false, false, false, false, true, false, false, false, false, false, false, false, false, false, false, false, false, false, true, false, false, false, false, false, false, false, false, false, true, false, false, false, true, false, false, false, false, false, false, false], [false, false, false, false, false, false, false, true, false, false, false, false, false, false, false, false, false, false, false, false, false, true, false, false, false, false, false, false, false, true, true, true, true, true, true, true, true, true, true, false, false, false, false], [false, false, false, false, false, false, false, true, false, false, false, false, false, false, false, false, false, false, false, false, false, true, false, false, false, false, false, false, false, true, true, true, true, true, true, true, true, true, true, false, false, false, false], [false, false, false, false, false, false, false, true, true, true, true, true, true, true, true, true, true, true, true, true, true, true, true, true, true, true, true, true, true, true, true, true, true, true, true, true, true, true, true, false, false, false, false], [false, false, false, false, false, false, false, false, false, false, false, false, false, false, false, false, false, false, false, false, false, false, false, false, false, false, false, false, false, true, true, true, true, true, true, true, true, true, true, false, false, false, false], [false, false, false, false, false, false, false, false, false, false, false, false, false, false, false, false, false, false, false, false, false, false, false, false, false, false, false, false, false, true, true, true, true, true, true, true, true, true, true, false, false, false, false], [false, false, false, false, false, false, false, false, false, false, false, false, false, false, false, false, false, false, false, false, false, false, false, false, false, false, false, false, false, true, true, true, true, true, true, true, true, true, true, false, false, false, false], [false, false, false, false, false, false, false, false, false, false, false, false, false, false, false, false, false, false, false, false, false, false, false, false, false, false, false, false, false, false, false, true, false, false, false, true, false, false, false, false, false, false, false], [false, false, false, false, false, false, false, false, false, false, false, false, false, false, false, false, false, false, false, false, false, false, false, false, false, false, false, false, false, false, false, true, false, false, false, true, false, false, false, false, false, false, false], [false, false, false, false, false, false, false, false, false, false, false, true, true, true, true, true, true, true, false, false, false, false, false, false, false, false, false, false, false, false, false, true, false, false, false, true, false, false, false, false, false, false, false], [false, false, false, false, false, false, false, false, false, false, false, true, true, true, true, true, true, true, false, false, false, false, false, false, false, false, false, false, false, false, false, true, false, false, false, true, false, false, false, false, false, false, false], [false, false, false, false, false, false, false, false, false, false, false, true, true, true, true, true, true, true, false, false, false, false, false, false, false, false, false, false, false, false, false, true, false, false, false, true, false, false, false, false, false, false, false], [false, false, false, false, false, false, false, false, false, false, false, true, true, true, true, true, true, true, true, true, true, true, true, true, true, true, true, true, true, true, true, true, true, true, true, true, false, false, false, false, false, false, false], [false, false, false, false, false, false, false, false, false, false, false, true, true, true, true, true, true, true, false, false, false, false, false, false, false, false, false, false, false, false, false, false, false, false, false, false, false, false, false, false, false, false, false], [false, false, false, false, false, false, false, false, false, false, false, true, true, true, true, true, true, true, false, false, false, false, false, false, false, false, false, false, false, false, false, false, false, false, false, false, false, false, false, false, false, false, false], [false, false, false, false, false, false, false, false, false, false, false, true, true, true, true, true, true, true, false, false, false, false, false, false, false, false, false, false, false, false, false, false, false, false, false, false, false, false, false, false, false, false, false], [false, false, false, false, false, false, false, false, false, false, false, true, true, true, true, true, true, true, false, false, false, false, false, false, false, false, false, false, false, false, false, false, false, false, false, false, false, false, false, false, false, false, false], [false, false, false, false, false, false, false, false, false, false, false, false, false, false, false, false, false, false, false, false, false, false, false, false, false, false, false, false, false, false, false, false, false, false, false, false, false, false, false, false, false, false, false], [false, false, false, false, false, false, false, false, false, false, false, false, false, false, false, false, false, false, false, false, false, false, false, false, false, false, false, false, false, false, false, false, false, false, false, false, false, false, false, false, false, false, false], [false, false, false, false, false, false, false, false, false, false, false, false, false, false, false, false, false, false, false, false, false, false, false, false, false, false, false, false, false, false, false, false, false, false, false, false, false, false, false, false, false, false, false], [false, false, false, false, false, false, false, false, false, false, false, false, false, false, false, false, false, false, false, false, false, false, false, false, false, false, false, false, false, false, false, false, false, false, false, false, false, false, false, false, false, false, false], [false, false, false, false, false, false, false, false, false, false, false, false, false, false, false, false, false, false, false, false, false, false, false, false, false, false, false, false, false, false, false, false, false, false, false, false, false, false, false, false, false, false, false], [false, false, false, false, false, false, false, false, false, false, false, false, false, false, false, false, false, false, false, false, false, false, false, false, false, false, false, false, false, false, false, false, false, false, false, false, false, false, false, false, false, false, false], [false, false, false, false, false, false, false, false, false, false, false, false, false, false, false, false, false, false, false, false, false, false, false, false, false, false, false, false, false, false, false, false, false, false, false, false, false, false, false, false, false, false, false], [false, false, false, false, false, false, false, false, false, false, false, false, false, false, false, false, false, false, false, false, false, false, false, false, false, false, false, false, false, false, false, false, false, false, false, false, false, false, false, false, false, false, false]], "entities": [{"x": 39, "y": 12, "char": "G", "color": [200, 100, 100], "name": "Goblin Elite", "blocks": true, "hp": 15, "max_hp": 15, "power": 4, "defense": 2, "speed": 90, "intel_tier": 3, "is_commander": false, "home_position": [39, 12], "effects": {}}, {"x": 2, "y": 22, "char": "W", "color": [255, 0, 0], "name": "Goblin Warlord", "blocks": true, "hp": 30, "max_hp": 30, "power": 6, "defense": 3, "speed": 80, "intel_tier": 4, "is_commander": true, "home_position": [2, 22], "effects": {}}, {"x": 50, "y": 33, "char": "g", "color": [100, 200, 100], "name": "Goblin Scout", "blocks": true, "hp": 5, "max_hp": 5, "power": 2, "defense": 0, "speed": 120, "intel_tier": 1, "is_commander": false, "home_position": [50, 33], "effects": {}}, {"x": 77, "y": 41, "char": "W", "color": [255, 0, 0], "name": "Goblin Warlord", "blocks": true, "hp": 30, "max_hp": 30, "power": 6, "defense": 3, "speed": 80, "intel_tier": 4, "is_commander": true, "home_position": [77, 41], "effects": {}}, {"x": 77, "y": 31, "char": "s", "color": [100, 200, 100], "name": "Goblin Soldier", "blocks": true, "hp": 10, "max_hp": 10, "power": 3, "defense": 1, "speed": 100, "intel_tier": 2, "is_commander": false, "home_position": [77, 31], "effects": {}}, {"x": 72, "y": 19, "char": "s", "color": [100, 200, 100], "name": "Goblin Soldier", "blocks": true, "hp": 10, "max_hp": 10, "power": 3, "defense": 1, "speed": 100, "intel_tier": 2, "is_commander": false, "home_position": [72, 19], "effects": {}}, {"x": 50, "y": 38, "char": "g", "color": [100, 200, 100], "name": "Goblin Scout", "blocks": true, "hp": 5, "max_hp": 5, "power": 2, "defense": 0, "speed": 120, "intel_tier": 1, "is_commander": false, "home_position": [50, 38], "effects": {}}, {"x": 49, "y": 38, "char": "s", "color": [100, 200, 100], "name": "Goblin Soldier", "blocks": true, "hp": 10, "max_hp": 10, "power": 3, "defense": 1, "speed": 100, "intel_tier": 2, "is_commander": false, "home_position": [49, 38], "effects": {}}, {"x": 71, "y": 35, "char": "/", "color": [255, 255, 255], "name": "iron_longsword", "blocks": false, "hp": 1, "max_hp": 1, "power": 0, "defense": 0, "speed": 0, "intel_tier": 0, "is_commander": false, "home_position": [0, 0], "effects": {}}, {"x": 27, "y": 39, "char": "/", "color": [255, 255, 255], "name": "steel_dagger", "blocks": false, "hp": 1, "max_hp": 1, "power": 0, "defense": 0, "speed": 0, "intel_tier": 0, "is_commander": false, "home_position": [0, 0], "effects": {}}, {"x": 21, "y": 41, "char": "/", "color": [255, 255, 255], "name": "apprentice_staff", "blocks": false, "hp": 1, "max_hp": 1, "power": 0, "defense": 0, "speed": 0, "intel_tier": 0, "is_commander": false, "home_position": [0, 0], "effects": {}}, {"x": 8, "y": 41, "char": "/", "color": [255, 255, 255], "name": "iron_mace", "blocks": false, "hp": 1, "max_hp": 1, "power": 0, "defense": 0, "speed": 0, "intel_tier": 0, "is_commander": false, "home_position": [0, 0], "effects": {}}, {"x": 44, "y": 41, "char": "[", "color": [255, 255, 255], "name": "chain_mail", "blocks": false, "hp": 1, "max_hp": 1, "power": 0, "defense": 0, "speed": 0, "intel_tier": 0, "is_commander": false, "home_position": [0, 0], "effects": {}}, {"x": 70, "y": 32, "char": "[", "color": [255, 255, 255], "name": "leather_armor", "blocks": false, "hp": 1, "max_hp": 1, "power": 0, "defense": 0, "speed": 0, "intel_tier": 0, "is_commander": false, "home_position": [0, 0], "effects": {}}, {"x": 34, "y": 19, "char": "[", "color": [255, 255, 255], "name": "scale_mail", "blocks": false, "hp": 1, "max_hp": 1, "power": 0, "defense": 0, "speed": 0, "intel_tier": 0, "is_commander": false, "home_position": [0, 0], "effects": {}}, {"x": 56, "y": 19, "char": "[", "color": [255, 255, 255], "name": "robe", "blocks": false, "hp": 1, "max_hp": 1, "power": 0, "defense": 0, "speed": 0, "intel_tier": 0, "is_commander": false, "home_position": [0, 0], "effects": {}}, {"x": 6, "y": 14, "char": "[", "color": [255, 255, 255], "name": "wooden_shield", "blocks": false, "hp": 1, "max_hp": 1, "power": 0, "defense": 0, "speed": 0, "intel_tier": 0, "is_commander": false, "home_position": [0, 0], "effects": {}}, {"x": 61, "y": 27, "char": "*", "color": [255, 255, 255], "name": "holy_symbol", "blocks": false, "hp": 1, "max_hp": 1, "power": 0, "defense": 0, "speed": 0, "intel_tier": 0, "is_commander": false, "home_position": [0, 0], "effects": {}}, {"x": 66, "y": 1, "char": "*", "color": [255, 255, 255], "name": "lockpicks_5", "blocks": false, "hp": 1, "max_hp": 1, "power": 0, "defense": 0, "speed": 0, "intel_tier": 0, "is_commander": false, "home_position": [0, 0], "effects": {}}, {"x": 75, "y": 3, "char": ",", "color": [255, 255, 255], "name": "ration_3", "blocks": false, "hp": 1, "max_hp": 1, "power": 0, "defense": 0, "speed": 0, "intel_tier": 0, "is_commander": false, "home_position": [0, 0], "effects": {}}, {"x": 37, "y": 11, "char": "!", "color": [255, 255, 255], "name": "healing_potion", "blocks": false, "hp": 1, "max_hp": 1, "power": 0, "defense": 0, "speed": 0, "intel_tier": 0, "is_commander": false, "home_position": [0, 0], "effects": {}}, {"x": 69, "y": 31, "char": "?", "color": [255, 255, 255], "name": "spellbook_fire", "blocks": false, "hp": 1, "max_hp": 1, "power": 0, "defense": 0, "speed": 0, "intel_tier": 0, "is_commander": false, "home_position": [0, 0], "effects": {}}], "energy_system": [{"entity": {"x": 10, "y": 10, "char": "@", "color": [255, 255, 0], "name": "Adventurer", "blocks": true, "hp": 15, "max_hp": 23, "power": 5, "defense": 2, "speed": 100, "intel_tier": 3, "is_commander": false, "home_position": [18, 2], "effects": {}}, "energy": 100, "speed": 100}, {"entity": {"x": 39, "y": 12, "char": "G", "color": [200, 100, 100], "name": "Goblin Elite", "blocks": true, "hp": 15, "max_hp": 15, "power": 4, "defense": 2, "speed": 90, "intel_tier": 3, "is_commander": false, "home_position": [39, 12], "effects": {}}, "energy": 0, "speed": 90}, {"entity": {"x": 2, "y": 22, "char": "W", "color": [255, 0, 0], "name": "Goblin Warlord", "blocks": true, "hp": 30, "max_hp": 30, "power": 6, "defense": 3, "speed": 80, "intel_tier": 4, "is_commander": true, "home_position": [2, 22], "effects": {}}, "energy": 0, "speed": 80}, {"entity": {"x": 50, "y": 33, "char": "g", "color": [100, 200, 100], "name": "Goblin Scout", "blocks": true, "hp": 5, "max_hp": 5, "power": 2, "defense": 0, "speed": 120, "intel_tier": 1, "is_commander": false, "home_position": [50, 33], "effects": {}}, "energy": 0, "speed": 120}, {"entity": {"x": 77, "y": 41, "char": "W", "color": [255, 0, 0], "name": "Goblin Warlord", "blocks": true, "hp": 30, "max_hp": 30, "power": 6, "defense": 3, "speed": 80, "intel_tier": 4, "is_commander": true, "home_position": [77, 41], "effects": {}}, "energy": 0, "speed": 80}, {"entity": {"x": 77, "y": 31, "char": "s", "color": [100, 200, 100], "name": "Goblin Soldier", "blocks": true, "hp": 10, "max_hp": 10, "power": 3, "defense": 1, "speed": 100, "intel_tier": 2, "is_commander": false, "home_position": [77, 31], "effects": {}}, "energy": 0, "speed": 100}, {"entity": {"x": 72, "y": 19, "char": "s", "color": [100, 200, 100], "name": "Goblin Soldier", "blocks": true, "hp": 10, "max_hp": 10, "power": 3, "defense": 1, "speed": 100, "intel_tier": 2, "is_commander": false, "home_position": [72, 19], "effects": {}}, "energy": 0, "speed": 100}, {"entity": {"x": 50, "y": 38, "char": "g", "color": [100, 200, 100], "name": "Goblin Scout", "blocks": true, "hp": 5, "max_hp": 5, "power": 2, "defense": 0, "speed": 120, "intel_tier": 1, "is_commander": false, "home_position": [50, 38], "effects": {}}, "energy": 0, "speed": 120}, {"entity": {"x": 49, "y": 38, "char": "s", "color": [100, 200, 100], "name": "Goblin Soldier", "blocks": true, "hp": 10, "max_hp": 10, "power": 3, "defense": 1, "speed": 100, "intel_tier": 2, "is_commander": false, "home_position": [49, 38], "effects": {}}, "energy": 0, "speed": 100}, {"entity": {"x": 71, "y": 35, "char": "/", "color": [255, 255, 255], "name": "iron_longsword", "blocks": false, "hp": 1, "max_hp": 1, "power": 0, "defense": 0, "speed": 0, "intel_tier": 0, "is_commander": false, "home_position": [0, 0], "effects": {}}, "energy": 0, "speed": 0}, {"entity": {"x": 27, "y": 39, "char": "/", "color": [255, 255, 255], "name": "steel_dagger", "blocks": false, "hp": 1, "max_hp": 1, "power": 0, "defense": 0, "speed": 0, "intel_tier": 0, "is_commander": false, "home_position": [0, 0], "effects": {}}, "energy": 0, "speed": 0}, {"entity": {"x": 21, "y": 41, "char": "/", "color": [255, 255, 255], "name": "apprentice_staff", "blocks": false, "hp": 1, "max_hp": 1, "power": 0, "defense": 0, "speed": 0, "intel_tier": 0, "is_commander": false, "home_position": [0, 0], "effects": {}}, "energy": 0, "speed": 0}, {"entity": {"x": 8, "y": 41, "char": "/", "color": [255, 255, 255], "name": "iron_mace", "blocks": false, "hp": 1, "max_hp": 1, "power": 0, "defense": 0, "speed": 0, "intel_tier": 0, "is_commander": false, "home_position": [0, 0], "effects": {}}, "energy": 0, "speed": 0}, {"entity": {"x": 44, "y": 41, "char": "[", "color": [255, 255, 255], "name": "chain_mail", "blocks": false, "hp": 1, "max_hp": 1, "power": 0, "defense": 0, "speed": 0, "intel_tier": 0, "is_commander": false, "home_position": [0, 0], "effects": {}}, "energy": 0, "speed": 0}, {"entity": {"x": 70, "y": 32, "char": "[", "color": [255, 255, 255], "name": "leather_armor", "blocks": false, "hp": 1, "max_hp": 1, "power": 0, "defense": 0, "speed": 0, "intel_tier": 0, "is_commander": false, "home_position": [0, 0], "effects": {}}, "energy": 0, "speed": 0}, {"entity": {"x": 34, "y": 19, "char": "[", "color": [255, 255, 255], "name": "scale_mail", "blocks": false, "hp": 1, "max_hp": 1, "power": 0, "defense": 0, "speed": 0, "intel_tier": 0, "is_commander": false, "home_position": [0, 0], "effects": {}}, "energy": 0, "speed": 0}, {"entity": {"x": 56, "y": 19, "char": "[", "color": [255, 255, 255], "name": "robe", "blocks": false, "hp": 1, "max_hp": 1, "power": 0, "defense": 0, "speed": 0, "intel_tier": 0, "is_commander": false, "home_position": [0, 0], "effects": {}}, "energy": 0, "speed": 0}, {"entity": {"x": 6, "y": 14, "char": "[", "color": [255, 255, 255], "name": "wooden_shield", "blocks": false, "hp": 1, "max_hp": 1, "power": 0, "defense": 0, "speed": 0, "intel_tier": 0, "is_commander": false, "home_position": [0, 0], "effects": {}}, "energy": 0, "speed": 0}, {"entity": {"x": 61, "y": 27, "char": "*", "color": [255, 255, 255], "name": "holy_symbol", "blocks": false, "hp": 1, "max_hp": 1, "power": 0, "defense": 0, "speed": 0, "intel_tier": 0, "is_commander": false, "home_position": [0, 0], "effects": {}}, "energy": 0, "speed": 0}, {"entity": {"x": 66, "y": 1, "char": "*", "color": [255, 255, 255], "name": "lockpicks_5", "blocks": false, "hp": 1, "max_hp": 1, "power": 0, "defense": 0, "speed": 0, "intel_tier": 0, "is_commander": false, "home_position": [0, 0], "effects": {}}, "energy": 0, "speed": 0}, {"entity": {"x": 75, "y": 3, "char": ",", "color": [255, 255, 255], "name": "ration_3", "blocks": false, "hp": 1, "max_hp": 1, "power": 0, "defense": 0, "speed": 0, "intel_tier": 0, "is_commander": false, "home_position": [0, 0], "effects": {}}, "energy": 0, "speed": 0}, {"entity": {"x": 37, "y": 11, "char": "!", "color": [255, 255, 255], "name": "healing_potion", "blocks": false, "hp": 1, "max_hp": 1, "power": 0, "defense": 0, "speed": 0, "intel_tier": 0, "is_commander": false, "home_position": [0, 0], "effects": {}}, "energy": 0, "speed": 0}, {"entity": {"x": 69, "y": 31, "char": "?", "color": [255, 255, 255], "name": "spellbook_fire", "blocks": false, "hp": 1, "max_hp": 1, "power": 0, "defense": 0, "speed": 0, "intel_tier": 0, "is_commander": false, "home_position": [0, 0], "effects": {}}, "energy": 0, "speed": 0}]}